skrybe_sdk/__init__.py
skrybe_sdk/__main__.py
skrybe_sdk/exceptions.py
skrybe_sdk/sdk.py
skrybe_sdk-0.1.0.dist-info/licenses/LICENSE
skrybe_sdk-0.1.0.dist-info/METADATA
skrybe_sdk-0.1.0.dist-info/WHEEL
skrybe_sdk-0.1.0.dist-info/top_level.txt
skrybe_sdk-0.1.0.dist-info/RECORD
