Metadata-Version: 2.4
Name: skrybe-sdk
Version: 0.1.0
Summary: Django-compatible SDK for Skrybe API.
Home-page: https://dashboard.skry.be
Author: Your Name
Classifier: Programming Language :: Python :: 3
Classifier: License :: OSI Approved :: MIT License
Classifier: Operating System :: OS Independent
Requires-Python: >=3.7
License-File: LICENSE
Requires-Dist: requests>=2.0.0
Dynamic: author
Dynamic: classifier
Dynamic: home-page
Dynamic: license-file
Dynamic: requires-dist
Dynamic: requires-python
Dynamic: summary
